VLEIsoTracer.cp39-win_amd64.pyd
VLEIsoTracer-0.10.2.dist-info/METADATA
VLEIsoTracer-0.10.2.dist-info/WHEEL
VLEIsoTracer-0.10.2.dist-info/top_level.txt
VLEIsoTracer-0.10.2.dist-info/RECORD
