Metadata-Version: 2.1
Name: VLEIsoTracer
Version: 0.10.2
Summary: Tracer for isolines of VLE phase envelopes
Home-page: UNKNOWN
Author: Ian Bell
Author-email: ian.bell@nist.gov
License: UNKNOWN
Platform: UNKNOWN
